<?xml version="1.0"?>
<calendarium><ordo id="RE"><messe>perannum_24-3</messe><priorite>13</priorite><pV/><couleur>Vert</couleur><reference/><sanctoral><la/><fr/></sanctoral><tempus><la>Tempus per annum</la><fr>Temps dans l'ann&#xE9;e</fr></tempus><hebdomada><la>Hebdomada XXIV per annum</la><fr>XXIV&#xE8;me semaine dans l'ann&#xE9;e</fr></hebdomada><intitule><la/><fr/></intitule><rang><la/><fr/></rang><hebdomada_psalterium>4</hebdomada_psalterium><phase_lunaire>4,32</phase_lunaire><age_lunaire>1</age_lunaire><selection>St Joseph de Cupertino</selection><matin>
		<temps>Tempus per annum</temps>
		<psautier>psautier_43</psautier>
		<psalterium>psalterium_43</psalterium>
		<ferie>perannum_43</ferie>
		<special/>
		<propre/>
		<lettre_annee>B</lettre_annee>
		<cel/>
	</matin><soir>
		<temps>Tempus per annum</temps>
		<psautier>psautier_43</psautier>
		<psalterium>psalterium_43</psalterium>
		<ferie>perannum_43</ferie>
		<special/>
		<propre/>
		<lettre_annee>B</lettre_annee>	
		<premieresvepres>0</premieresvepres>
		<cel/>	
	</soir>	
<intitule_matin id="Dominica XXIV per annum"/>
<invitatoire id=""/>
<HYMNUS_lectures>HY_Nocte_surgentes_vigilemus_omnes</HYMNUS_lectures>
<HYMNUS_lec_jour>HY_Ad_preces_nostras_deitatis_aures</HYMNUS_lec_jour>
<antL1>AN_Clamor_meus_Domine</antL1>
<psL1>ps101I</psL1>
<antL2>AN_Respice_Domine_in</antL2>
<psL2>ps101II</psL2>
<antL3>AN_Tu_Domine_terram</antL3>
<psL3>ps101III</psL3>
<osb_vig_ant_attente id="AN_Ego_dormivi"/>
<osb_vig_ps_attente id=""/>
<Llec1/>
<Lrep1 id=""/>
<Llec2 id=""/>
<Lrep2 id=""/>
<Loratio id=""/>
<Levangile id=""/>
<Vant1>AN_Adiutor</Vant1>
<Vps1>ps45</Vps1>
<Vant2>AN_Iubilate_in_voce</Vant2>
<Vps2>ps46</Vps2>
<Vant3>AN_Magnus_Dominus</Vant3>
<Vps3>ps47</Vps3>
<Vant4>AN_Auribus_percipite</Vant4>
<Vps4>ps48</Vps4>
<Vant5>AN_Deus_deorum</Vant5>
<Vps5>ps49</Vps5>
<Vant6>AN_Confitebor_tibi</Vant6>
<Vps6>ps51</Vps6>
<Vlec1 id=""/>
<Vrep1 id=""/>
<Vlec2 id=""/>
<Vrep2 id=""/>
<Vlec3 id=""/>
<Vlrep3 id=""/>
<Vlec4 id=""/>
<Vrep4 id=""/>
<Vver1 id=""/>
<Vant7>AN_Alleluia_alleluia</Vant7>
<Vps7>ps52</Vps7>
<Vant8/>
<Vps8>ps53</Vps8>
<Vant9/>
<Vps9>ps54</Vps9>
<Vant10/>
<Vps10>ps55</Vps10>
<Vant11/>
<Vps11>ps57</Vps11>
<Vant12/>
<Vps12>ps58</Vps12>
<Vver2 id=""/>
<Vlec5 id=""/>
<Vrep5 id=""/>
<Vlec6 id=""/>
<Vrep6 id=""/>
<Vlec7 id=""/>
<Vrep7 id=""/>
<Vlec8 id=""/>
<Vrep8 id=""/>
<Vant13/>
<Vcant1 id=""/>
<Vcant2 id=""/>
<Vcant3 id=""/>
<Vver3 id=""/>
<Vev_debut id=""/>
<Vlec9 id=""/>
<Vrep9 id=""/>
<Vlec10 id=""/>
<Vrep10 id=""/>
<Vlec11 id=""/>
<Vrep11 id=""/>
<Vlec12 id=""/>
<Vevangile id=""/>
<Voraison id=""/>
<HYMNUS_laudes>hy_Aterne_lucis_conditor</HYMNUS_laudes>
<ant1>AN_Tibi_Domine_psallam</ant1>
<ps1>ps100</ps1>
<ant2>AN_Ne_auferas_Domine</ant2>
<ps2>AT39</ps2>
<ant3>AN_Deus_canticum_novum</ant3>
<ps3>ps143</ps3>
<LB_matin>LB_Is_55_1</LB_matin> 
<RB_matin>RB_Vocem_meam_audi_Domine</RB_matin> <benedictus>AN_De_manu_omnium</benedictus><laudes_preces>perannum_43</laudes_preces><oratio_laudes>COL_Auge_in_nobis_quaesumus_Domine_fidem</oratio_laudes>
<osb_laudes_ex_intitule id=""/>
<osb_laudes_ex_ps1 id=""/>
<osb_laudes_ex_ps2 id=""/>
<osb_laudes_ex_ps3 id=""/>
<osb_laudes_ex_ps4 id=""/>
<osb_laudes_ex_ps5 id=""/>
<osb_laudes_ex_ant1 id=""/>
<osb_laudes_ex_ant2 id=""/>
<osb_laudes_ex_ant3 id=""/>
<osb_laudes_ex_ant4 id=""/>
<osb_laudes_ex_ant5 id=""/>
<osb_laudes_ex_hymne id=""/>
<osb_laudes_ex_vers id=""/>
<osb_laudes_ex_LB id=""/>
<osb_laudes_ex_RB id=""/>
<osb_laudes_ex_benedictus id=""/>
<osb_laudes_ex_oratio id=""/>
<HYMNUS_3>hy_Certum_tenentes_ordinem</HYMNUS_3>
<HYMNUS_6>hy_Dicamus_laudes_Domino</HYMNUS_6>
<HYMNUS_9>hy_Ternis_horarum_terminis</HYMNUS_9>
<osb_sexte_ant id=""/>
<osb_none_ant id=""/>
<osb_sexte_ps1 id=""/>
<osb_sexte_ant2 id=""/>
<osb_sexte_ant3 id=""/>
<osb_none_ps1 id=""/>
<osb_none_ant2 id=""/>
<osb_none_ant3 id=""/>
<ant4>AN_Si_haec_scitis</ant4>
<ps4>ps118XVIII</ps4>
<ant5>AN_Intret_oratio_mea</ant5>
<ps5>ps87I</ps5>
<ant6>AN_Ad_te_Domine</ant6>
<ps6>ps87II</ps6>
<LB_3>LB_1_Io_3_17-18</LB_3>
<RB_3>VERS_Iucundus_homo</RB_3>
<LB_6>LB_Deut_30_11._14</LB_6>
<RB_6>VERS_Lucerna_pedibus</RB_6>
<LB_9>LB_Is_55_10-11</LB_9>
<RB_9>VERS_Emittit_Dominus</RB_9>
<oratio_3>COL_Omnipotens_sempiterne_Deus_qui_Paraclitum_Sanctum</oratio_3>
<oratio_6>COL_Deus_qui_Petro_salvificum_tuum_super </oratio_6>
<oratio_9>COL_Deus_qui_Cornelio_centurioni_angelum_tuum</oratio_9>
<intitule_soir><la/></intitule_soir>
<rang_soir><la/></rang_soir>
<office_soir><la/></office_soir>
<HYMNUS_vepres>hy_Sator_princepsque_temporum</HYMNUS_vepres>
<ant7>AN_Si_oblitus_fuero</ant7>
<ps7>ps136</ps7>
<ant8>AN_In_conspectu_angelorum</ant8>
<ps8>ps137</ps8>
<ant9>AN_Dignus_est_Agnus</ant9>
<ps9>NT9</ps9>
<LB_soir>LB_Col_3_16</LB_soir>
<RB_soir>RB_Adimplebis_me_laetitia</RB_soir>
<magnificat>AN_Fac_nobiscum_Domine</magnificat>
<vepres_preces>perannum_43</vepres_preces>
<oratio_vepres>COL_Orantes_in_conspectu_tuo_Domine_tuam</oratio_vepres>
<osb_vepres_ps1 id=""/>
<osb_vepres_ps2 id=""/>
<osb_vepres_ps3 id=""/>
<osb_vepres_ps4 id=""/>
<osb_vepres_ant1 id=""/>
<osb_vepres_ant2 id=""/>
<osb_vepres_ant3 id=""/>
<osb_vepres_ant4 id=""/>
<osb_vepres_hymne id=""/>
<osb_vepres_vers id=""/>
<osb_vepres_LB id=""/>
<osb_vepres_RB id=""/>
<osb_vepres_magnificat id=""/>
<osb_vepres_oratio id=""/>
<osb_vepres_ex_intitule id=""/>
<osb_vepres_ex_ps1 id=""/>
<osb_vepres_ex_ps2 id=""/>
<osb_vepres_ex_ps3 id=""/>
<osb_vepres_ex_ps4 id=""/>
<osb_vepres_ex_ant1 id=""/>
<osb_vepres_ex_ant2 id=""/>
<osb_vepres_ex_ant3 id=""/>
<osb_vepres_ex_ant4 id=""/>
<osb_vepres_ex_hymne id=""/>
<osb_vepres_ex_vers id=""/>
<osb_vepres_ex_LB id=""/>
<osb_vepres_ex_RB id=""/>
<osb_vepres_ex_magnificat id=""/>
<osb_vepres_ex_oratio id=""/>
		
<HYMNUS_complies>HY_Christe_qui_splendor</HYMNUS_complies>
<comp_ant1>AN_Tu_Domine_Deus</comp_ant1>
<comp_ps1>ps85</comp_ps1>
<comp_ant2/>
<comp_ps2/>
<comp_LB>LB_1_Th_5_9-10</comp_LB>
<comp_RB>RB_In_manus_tuas</comp_RB>
<comp_oratio>COL_Quietem_Domine_corporibus_nostris_tribue_salutarem</comp_oratio><comp_AM>Salve_regina</comp_AM><messe id="perannum_24-3">
<IN>IN_Da_pacem</IN>

<KY/>
<GLO/><COL>COL_Auge_in_nobis_quaesumus_Domine_fidem</COL>
<LEC1>1Cor12,12-31</LEC1>	
<PS1>GR_Laetatus_sum</PS1>
<LEC2/>
<PS2>AL_Timebunt_gentes</PS2>
<SEQ/>
<EV>EV_Lc7,11-17</EV>
<OF>OF_Sanctificavit</OF>
<SO/>
<PREF/>
<SAN/>
<CAN/>
<AGN/>
<CO>CO_Tollite_hostias</CO>
<PC/>
<ML_IN/>
<ML_PS/>
<ML_AL/>
<ML_CO/>
</messe>
</ordo><ordo id="SWF"><messe>perannum_24-3</messe><priorite>13</priorite><pV/><couleur>Vert</couleur><reference/><sanctoral><la/><fr/></sanctoral><tempus><la>Tempus per annum</la><fr>Temps dans l'ann&#xE9;e</fr></tempus><hebdomada><la>Hebdomada XXIV per annum</la><fr>XXIV&#xE8;me semaine dans l'ann&#xE9;e</fr></hebdomada><intitule><la/><fr/></intitule><rang><la/><fr/></rang><hebdomada_psalterium>4</hebdomada_psalterium><phase_lunaire>4,32</phase_lunaire><age_lunaire>1</age_lunaire><selection>St Joseph de Cupertino</selection><matin>
		<temps>Tempus per annum</temps>
		<psautier>psautier_43</psautier>
		<psalterium>psalterium_43</psalterium>
		<ferie>perannum_43</ferie>
		<special/>
		<propre/>
		<lettre_annee>B</lettre_annee>
		<cel/>
	</matin><soir>
		<temps>Tempus per annum</temps>
		<psautier>psautier_43</psautier>
		<psalterium>psalterium_43</psalterium>
		<ferie>perannum_43</ferie>
		<special/>
		<propre/>
		<lettre_annee>B</lettre_annee>	
		<premieresvepres>0</premieresvepres>
		<cel/>	
	</soir>	
<intitule_matin id="Dominica XXIV per annum"/>
<invitatoire id=""/>
<HYMNUS_lectures>HY_Nocte_surgentes_vigilemus_omnes</HYMNUS_lectures>
<HYMNUS_lec_jour>HY_Ad_preces_nostras_deitatis_aures</HYMNUS_lec_jour>
<antL1>AN_Clamor_meus_Domine</antL1>
<psL1>ps101I</psL1>
<antL2>AN_Respice_Domine_in</antL2>
<psL2>ps101II</psL2>
<antL3>AN_Tu_Domine_terram</antL3>
<psL3>ps101III</psL3>
<osb_vig_ant_attente id="AN_Ego_dormivi"/>
<osb_vig_ps_attente id=""/>
<Llec1/>
<Lrep1 id=""/>
<Llec2 id=""/>
<Lrep2 id=""/>
<Loratio id=""/>
<Levangile id=""/>
<Vant1>AN_Adiutor</Vant1>
<Vps1>ps45</Vps1>
<Vant2>AN_Iubilate_in_voce</Vant2>
<Vps2>ps46</Vps2>
<Vant3>AN_Magnus_Dominus</Vant3>
<Vps3>ps47</Vps3>
<Vant4>AN_Auribus_percipite</Vant4>
<Vps4>ps48</Vps4>
<Vant5>AN_Deus_deorum</Vant5>
<Vps5>ps49</Vps5>
<Vant6>AN_Confitebor_tibi</Vant6>
<Vps6>ps51</Vps6>
<Vlec1 id=""/>
<Vrep1 id=""/>
<Vlec2 id=""/>
<Vrep2 id=""/>
<Vlec3 id=""/>
<Vlrep3 id=""/>
<Vlec4 id=""/>
<Vrep4 id=""/>
<Vver1 id=""/>
<Vant7>AN_Alleluia_alleluia</Vant7>
<Vps7>ps52</Vps7>
<Vant8/>
<Vps8>ps53</Vps8>
<Vant9/>
<Vps9>ps54</Vps9>
<Vant10/>
<Vps10>ps55</Vps10>
<Vant11/>
<Vps11>ps57</Vps11>
<Vant12/>
<Vps12>ps58</Vps12>
<Vver2 id=""/>
<Vlec5 id=""/>
<Vrep5 id=""/>
<Vlec6 id=""/>
<Vrep6 id=""/>
<Vlec7 id=""/>
<Vrep7 id=""/>
<Vlec8 id=""/>
<Vrep8 id=""/>
<Vant13/>
<Vcant1 id=""/>
<Vcant2 id=""/>
<Vcant3 id=""/>
<Vver3 id=""/>
<Vev_debut id=""/>
<Vlec9 id=""/>
<Vrep9 id=""/>
<Vlec10 id=""/>
<Vrep10 id=""/>
<Vlec11 id=""/>
<Vrep11 id=""/>
<Vlec12 id=""/>
<Vevangile id=""/>
<Voraison id=""/>
<HYMNUS_laudes>hy_Aterne_lucis_conditor</HYMNUS_laudes>
<ant1>AN_Tibi_Domine_psallam</ant1>
<ps1>ps100</ps1>
<ant2>AN_Ne_auferas_Domine</ant2>
<ps2>AT39</ps2>
<ant3>AN_Deus_canticum_novum</ant3>
<ps3>ps143</ps3>
<LB_matin>LB_Is_55_1</LB_matin> 
<RB_matin>RB_Vocem_meam_audi_Domine</RB_matin> <benedictus>AN_De_manu_omnium</benedictus><laudes_preces>perannum_43</laudes_preces><oratio_laudes>COL_Auge_in_nobis_quaesumus_Domine_fidem</oratio_laudes>
<osb_laudes_ex_intitule id=""/>
<osb_laudes_ex_ps1 id=""/>
<osb_laudes_ex_ps2 id=""/>
<osb_laudes_ex_ps3 id=""/>
<osb_laudes_ex_ps4 id=""/>
<osb_laudes_ex_ps5 id=""/>
<osb_laudes_ex_ant1 id=""/>
<osb_laudes_ex_ant2 id=""/>
<osb_laudes_ex_ant3 id=""/>
<osb_laudes_ex_ant4 id=""/>
<osb_laudes_ex_ant5 id=""/>
<osb_laudes_ex_hymne id=""/>
<osb_laudes_ex_vers id=""/>
<osb_laudes_ex_LB id=""/>
<osb_laudes_ex_RB id=""/>
<osb_laudes_ex_benedictus id=""/>
<osb_laudes_ex_oratio id=""/>
<HYMNUS_3>hy_Certum_tenentes_ordinem</HYMNUS_3>
<HYMNUS_6>hy_Dicamus_laudes_Domino</HYMNUS_6>
<HYMNUS_9>hy_Ternis_horarum_terminis</HYMNUS_9>
<osb_sexte_ant id=""/>
<osb_none_ant id=""/>
<osb_sexte_ps1 id=""/>
<osb_sexte_ant2 id=""/>
<osb_sexte_ant3 id=""/>
<osb_none_ps1 id=""/>
<osb_none_ant2 id=""/>
<osb_none_ant3 id=""/>
<ant4>AN_Si_haec_scitis</ant4>
<ps4>ps118XVIII</ps4>
<ant5>AN_Intret_oratio_mea</ant5>
<ps5>ps87I</ps5>
<ant6>AN_Ad_te_Domine</ant6>
<ps6>ps87II</ps6>
<LB_3>LB_1_Io_3_17-18</LB_3>
<RB_3>VERS_Iucundus_homo</RB_3>
<LB_6>LB_Deut_30_11._14</LB_6>
<RB_6>VERS_Lucerna_pedibus</RB_6>
<LB_9>LB_Is_55_10-11</LB_9>
<RB_9>VERS_Emittit_Dominus</RB_9>
<oratio_3>COL_Omnipotens_sempiterne_Deus_qui_Paraclitum_Sanctum</oratio_3>
<oratio_6>COL_Deus_qui_Petro_salvificum_tuum_super </oratio_6>
<oratio_9>COL_Deus_qui_Cornelio_centurioni_angelum_tuum</oratio_9>
<intitule_soir><la/></intitule_soir>
<rang_soir><la/></rang_soir>
<office_soir><la/></office_soir>
<HYMNUS_vepres>hy_Sator_princepsque_temporum</HYMNUS_vepres>
<ant7>AN_Si_oblitus_fuero</ant7>
<ps7>ps136</ps7>
<ant8>AN_In_conspectu_angelorum</ant8>
<ps8>ps137</ps8>
<ant9>AN_Dignus_est_Agnus</ant9>
<ps9>NT9</ps9>
<LB_soir>LB_Col_3_16</LB_soir>
<RB_soir>RB_Adimplebis_me_laetitia</RB_soir>
<magnificat>AN_Fac_nobiscum_Domine</magnificat>
<vepres_preces>perannum_43</vepres_preces>
<oratio_vepres>COL_Orantes_in_conspectu_tuo_Domine_tuam</oratio_vepres>
<osb_vepres_ps1 id=""/>
<osb_vepres_ps2 id=""/>
<osb_vepres_ps3 id=""/>
<osb_vepres_ps4 id=""/>
<osb_vepres_ant1 id=""/>
<osb_vepres_ant2 id=""/>
<osb_vepres_ant3 id=""/>
<osb_vepres_ant4 id=""/>
<osb_vepres_hymne id=""/>
<osb_vepres_vers id=""/>
<osb_vepres_LB id=""/>
<osb_vepres_RB id=""/>
<osb_vepres_magnificat id=""/>
<osb_vepres_oratio id=""/>
<osb_vepres_ex_intitule id=""/>
<osb_vepres_ex_ps1 id=""/>
<osb_vepres_ex_ps2 id=""/>
<osb_vepres_ex_ps3 id=""/>
<osb_vepres_ex_ps4 id=""/>
<osb_vepres_ex_ant1 id=""/>
<osb_vepres_ex_ant2 id=""/>
<osb_vepres_ex_ant3 id=""/>
<osb_vepres_ex_ant4 id=""/>
<osb_vepres_ex_hymne id=""/>
<osb_vepres_ex_vers id=""/>
<osb_vepres_ex_LB id=""/>
<osb_vepres_ex_RB id=""/>
<osb_vepres_ex_magnificat id=""/>
<osb_vepres_ex_oratio id=""/>
		
<HYMNUS_complies>HY_Christe_qui_splendor</HYMNUS_complies>
<comp_ant1>AN_Tu_Domine_Deus</comp_ant1>
<comp_ps1>ps85</comp_ps1>
<comp_ant2/>
<comp_ps2/>
<comp_LB>LB_1_Th_5_9-10</comp_LB>
<comp_RB>RB_In_manus_tuas</comp_RB>
<comp_oratio>COL_Quietem_Domine_corporibus_nostris_tribue_salutarem</comp_oratio><comp_AM>Salve_regina</comp_AM><messe id="perannum_24-3">
<IN>IN_Da_pacem</IN>

<KY/>
<GLO/><COL>COL_Auge_in_nobis_quaesumus_Domine_fidem</COL>
<LEC1>1Cor12,12-31</LEC1>	
<PS1>GR_Laetatus_sum</PS1>
<LEC2/>
<PS2>AL_Timebunt_gentes</PS2>
<SEQ/>
<EV>EV_Lc7,11-17</EV>
<OF>OF_Sanctificavit</OF>
<SO/>
<PREF/>
<SAN/>
<CAN/>
<AGN/>
<CO>CO_Tollite_hostias</CO>
<PC/>
<ML_IN/>
<ML_PS/>
<ML_AL/>
<ML_CO/>
</messe>
</ordo><ordo id="SMK"><messe>perannum_24-3</messe><priorite>13</priorite><pV/><couleur>Vert</couleur><reference/><sanctoral><la/><fr/></sanctoral><tempus><la>Tempus per annum</la><fr>Temps dans l'ann&#xE9;e</fr></tempus><hebdomada><la>Hebdomada XXIV per annum</la><fr>XXIV&#xE8;me semaine dans l'ann&#xE9;e</fr></hebdomada><intitule><la/><fr/></intitule><rang><la/><fr/></rang><hebdomada_psalterium>4</hebdomada_psalterium><phase_lunaire>4,32</phase_lunaire><age_lunaire>1</age_lunaire><selection>St Joseph de Cupertino</selection><matin>
		<temps>Tempus per annum</temps>
		<psautier>psautier_43</psautier>
		<psalterium>psalterium_43</psalterium>
		<ferie>perannum_43</ferie>
		<special/>
		<propre/>
		<lettre_annee>B</lettre_annee>
		<cel/>
	</matin><soir>
		<temps>Tempus per annum</temps>
		<psautier>psautier_43</psautier>
		<psalterium>psalterium_43</psalterium>
		<ferie>perannum_43</ferie>
		<special/>
		<propre/>
		<lettre_annee>B</lettre_annee>	
		<premieresvepres>0</premieresvepres>
		<cel/>	
	</soir>	
<intitule_matin id="Dominica XXIV per annum"/>
<invitatoire id=""/>
<HYMNUS_lectures>HY_Nocte_surgentes_vigilemus_omnes</HYMNUS_lectures>
<HYMNUS_lec_jour>HY_Ad_preces_nostras_deitatis_aures</HYMNUS_lec_jour>
<antL1>AN_Clamor_meus_Domine</antL1>
<psL1>ps101I</psL1>
<antL2>AN_Respice_Domine_in</antL2>
<psL2>ps101II</psL2>
<antL3>AN_Tu_Domine_terram</antL3>
<psL3>ps101III</psL3>
<osb_vig_ant_attente id="AN_Ego_dormivi"/>
<osb_vig_ps_attente id=""/>
<Llec1/>
<Lrep1 id=""/>
<Llec2 id=""/>
<Lrep2 id=""/>
<Loratio id=""/>
<Levangile id=""/>
<Vant1>AN_Adiutor</Vant1>
<Vps1>ps45</Vps1>
<Vant2>AN_Iubilate_in_voce</Vant2>
<Vps2>ps46</Vps2>
<Vant3>AN_Magnus_Dominus</Vant3>
<Vps3>ps47</Vps3>
<Vant4>AN_Auribus_percipite</Vant4>
<Vps4>ps48</Vps4>
<Vant5>AN_Deus_deorum</Vant5>
<Vps5>ps49</Vps5>
<Vant6>AN_Confitebor_tibi</Vant6>
<Vps6>ps51</Vps6>
<Vlec1 id=""/>
<Vrep1 id=""/>
<Vlec2 id=""/>
<Vrep2 id=""/>
<Vlec3 id=""/>
<Vlrep3 id=""/>
<Vlec4 id=""/>
<Vrep4 id=""/>
<Vver1 id=""/>
<Vant7>AN_Alleluia_alleluia</Vant7>
<Vps7>ps52</Vps7>
<Vant8/>
<Vps8>ps53</Vps8>
<Vant9/>
<Vps9>ps54</Vps9>
<Vant10/>
<Vps10>ps55</Vps10>
<Vant11/>
<Vps11>ps57</Vps11>
<Vant12/>
<Vps12>ps58</Vps12>
<Vver2 id=""/>
<Vlec5 id=""/>
<Vrep5 id=""/>
<Vlec6 id=""/>
<Vrep6 id=""/>
<Vlec7 id=""/>
<Vrep7 id=""/>
<Vlec8 id=""/>
<Vrep8 id=""/>
<Vant13/>
<Vcant1 id=""/>
<Vcant2 id=""/>
<Vcant3 id=""/>
<Vver3 id=""/>
<Vev_debut id=""/>
<Vlec9 id=""/>
<Vrep9 id=""/>
<Vlec10 id=""/>
<Vrep10 id=""/>
<Vlec11 id=""/>
<Vrep11 id=""/>
<Vlec12 id=""/>
<Vevangile id=""/>
<Voraison id=""/>
<HYMNUS_laudes>hy_Aterne_lucis_conditor</HYMNUS_laudes>
<ant1>AN_Tibi_Domine_psallam</ant1>
<ps1>ps100</ps1>
<ant2>AN_Ne_auferas_Domine</ant2>
<ps2>AT39</ps2>
<ant3>AN_Deus_canticum_novum</ant3>
<ps3>ps143</ps3>
<LB_matin>LB_Is_55_1</LB_matin> 
<RB_matin>RB_Vocem_meam_audi_Domine</RB_matin> <benedictus>AN_De_manu_omnium</benedictus><laudes_preces>perannum_43</laudes_preces><oratio_laudes>COL_Auge_in_nobis_quaesumus_Domine_fidem</oratio_laudes>
<osb_laudes_ex_intitule id=""/>
<osb_laudes_ex_ps1 id=""/>
<osb_laudes_ex_ps2 id=""/>
<osb_laudes_ex_ps3 id=""/>
<osb_laudes_ex_ps4 id=""/>
<osb_laudes_ex_ps5 id=""/>
<osb_laudes_ex_ant1 id=""/>
<osb_laudes_ex_ant2 id=""/>
<osb_laudes_ex_ant3 id=""/>
<osb_laudes_ex_ant4 id=""/>
<osb_laudes_ex_ant5 id=""/>
<osb_laudes_ex_hymne id=""/>
<osb_laudes_ex_vers id=""/>
<osb_laudes_ex_LB id=""/>
<osb_laudes_ex_RB id=""/>
<osb_laudes_ex_benedictus id=""/>
<osb_laudes_ex_oratio id=""/>
<HYMNUS_3>hy_Certum_tenentes_ordinem</HYMNUS_3>
<HYMNUS_6>hy_Dicamus_laudes_Domino</HYMNUS_6>
<HYMNUS_9>hy_Ternis_horarum_terminis</HYMNUS_9>
<osb_sexte_ant id=""/>
<osb_none_ant id=""/>
<osb_sexte_ps1 id=""/>
<osb_sexte_ant2 id=""/>
<osb_sexte_ant3 id=""/>
<osb_none_ps1 id=""/>
<osb_none_ant2 id=""/>
<osb_none_ant3 id=""/>
<ant4>AN_Si_haec_scitis</ant4>
<ps4>ps118XVIII</ps4>
<ant5>AN_Intret_oratio_mea</ant5>
<ps5>ps87I</ps5>
<ant6>AN_Ad_te_Domine</ant6>
<ps6>ps87II</ps6>
<LB_3>LB_1_Io_3_17-18</LB_3>
<RB_3>VERS_Iucundus_homo</RB_3>
<LB_6>LB_Deut_30_11._14</LB_6>
<RB_6>VERS_Lucerna_pedibus</RB_6>
<LB_9>LB_Is_55_10-11</LB_9>
<RB_9>VERS_Emittit_Dominus</RB_9>
<oratio_3>COL_Omnipotens_sempiterne_Deus_qui_Paraclitum_Sanctum</oratio_3>
<oratio_6>COL_Deus_qui_Petro_salvificum_tuum_super </oratio_6>
<oratio_9>COL_Deus_qui_Cornelio_centurioni_angelum_tuum</oratio_9>
<intitule_soir><la/></intitule_soir>
<rang_soir><la/></rang_soir>
<office_soir><la/></office_soir>
<HYMNUS_vepres>hy_Sator_princepsque_temporum</HYMNUS_vepres>
<ant7>AN_Si_oblitus_fuero</ant7>
<ps7>ps136</ps7>
<ant8>AN_In_conspectu_angelorum</ant8>
<ps8>ps137</ps8>
<ant9>AN_Dignus_est_Agnus</ant9>
<ps9>NT9</ps9>
<LB_soir>LB_Col_3_16</LB_soir>
<RB_soir>RB_Adimplebis_me_laetitia</RB_soir>
<magnificat>AN_Fac_nobiscum_Domine</magnificat>
<vepres_preces>perannum_43</vepres_preces>
<oratio_vepres>COL_Orantes_in_conspectu_tuo_Domine_tuam</oratio_vepres>
<osb_vepres_ps1 id=""/>
<osb_vepres_ps2 id=""/>
<osb_vepres_ps3 id=""/>
<osb_vepres_ps4 id=""/>
<osb_vepres_ant1 id=""/>
<osb_vepres_ant2 id=""/>
<osb_vepres_ant3 id=""/>
<osb_vepres_ant4 id=""/>
<osb_vepres_hymne id=""/>
<osb_vepres_vers id=""/>
<osb_vepres_LB id=""/>
<osb_vepres_RB id=""/>
<osb_vepres_magnificat id=""/>
<osb_vepres_oratio id=""/>
<osb_vepres_ex_intitule id=""/>
<osb_vepres_ex_ps1 id=""/>
<osb_vepres_ex_ps2 id=""/>
<osb_vepres_ex_ps3 id=""/>
<osb_vepres_ex_ps4 id=""/>
<osb_vepres_ex_ant1 id=""/>
<osb_vepres_ex_ant2 id=""/>
<osb_vepres_ex_ant3 id=""/>
<osb_vepres_ex_ant4 id=""/>
<osb_vepres_ex_hymne id=""/>
<osb_vepres_ex_vers id=""/>
<osb_vepres_ex_LB id=""/>
<osb_vepres_ex_RB id=""/>
<osb_vepres_ex_magnificat id=""/>
<osb_vepres_ex_oratio id=""/>
		
<HYMNUS_complies>HY_Christe_qui_splendor</HYMNUS_complies>
<comp_ant1>AN_Tu_Domine_Deus</comp_ant1>
<comp_ps1>ps85</comp_ps1>
<comp_ant2/>
<comp_ps2/>
<comp_LB>LB_1_Th_5_9-10</comp_LB>
<comp_RB>RB_In_manus_tuas</comp_RB>
<comp_oratio>COL_Quietem_Domine_corporibus_nostris_tribue_salutarem</comp_oratio><comp_AM>Salve_regina</comp_AM><messe id="perannum_24-3">
<IN>IN_Da_pacem</IN>

<KY/>
<GLO/><COL>COL_Auge_in_nobis_quaesumus_Domine_fidem</COL>
<LEC1>1Cor12,12-31</LEC1>	
<PS1>GR_Laetatus_sum</PS1>
<LEC2/>
<PS2>AL_Timebunt_gentes</PS2>
<SEQ/>
<EV>EV_Lc7,11-17</EV>
<OF>OF_Sanctificavit</OF>
<SO/>
<PREF/>
<SAN/>
<CAN/>
<AGN/>
<CO>CO_Tollite_hostias</CO>
<PC/>
<ML_IN/>
<ML_PS/>
<ML_AL/>
<ML_CO/>
</messe>
</ordo><viergemarie>
 <intitule> </intitule></viergemarie><jerusalem/><piete>
 <intitule/></piete><calendriercivil>
 <intitule/></calendriercivil><journeesdediees>
 <intitule/></journeesdediees><biographie>
 <intitule>St Joseph de Cupertino</intitule>
 <biographiecourte>Pr&#xEA;tre franciscain, il re&#xE7;ut de nombreuses gr&#xE2;ces, dont la l&#xE9;vitation. Il dut se cacher pour vivre humblement (&#x2020;1663)</biographiecourte>
 <canonisebeatifie/>
 <patronage>Patron des candidats aux examens</patronage></biographie><martyrologe><para id="0">(Au Luxembourg : M&#xE9;moire de saint Lambert, du 17, n&#xB0; 3.)</para><para id="1">1. &#xC0; Nicom&#xE9;die en Bithynie, saint Oc&#xE9;an, martyr. </para><para id="2">2. &#xC0; Prymnesse en Phrygie, sainte Ariadne, martyre. </para><para id="3">3. Au territoire de Vienne en Gaule, au IIIe si&#xE8;cle saint Ferr&#xE9;ol, martyr. On rapporte qu&#x2019;&#xE9;lev&#xE9; &#xE0; la dignit&#xE9; de tribun, il refusa, au moment de la pers&#xE9;cution, d&#x2019;arr&#xEA;ter les chr&#xE9;tiens et que, saisi sur l&#x2019;ordre du pr&#xE9;fet, il fut tr&#xE8;s cruellement battu de verges et enferm&#xE9; dans un cachot, d&#x2019;o&#xF9; il s&#x2019;&#xE9;vada, mais, repris par ceux qui le poursuivaient et d&#xE9;capit&#xE9;, il obtint ainsi la palme du martyre.</para><para id="4">4. &#xC0; Milan, vers 355, saint Eustorge, &#xE9;v&#xEA;que, que saint Athanase loue d&#x2019;avoir confess&#xE9; la vraie foi contre les erreurs des ariens. </para><para id="5">5*. &#xC0; Avranches, au VIe si&#xE8;cle, saint Senier, &#xE9;v&#xEA;que. </para><para id="6">6. &#xC0; Limoges, &#xE0; la fin du VIe si&#xE8;cle, saint Ferr&#xE9;ol, &#xE9;v&#xEA;que. Lors d&#x2019;une &#xE9;meute en ville, alors que le peuple voulait mettre &#xE0; mort Marc, r&#xE9;f&#xE9;rendaire du roi Childebert, l&#x2019;&#xE9;v&#xEA;que l&#x2019;arracha au p&#xE9;ril qui le mena&#xE7;ait. </para><para id="7">7. &#xC0; Gortyne en Cr&#xE8;te, au VIIe si&#xE8;cle, saint Eum&#xE8;ne, &#xE9;v&#xEA;que. </para><para id="8">8*. &#xC0; Andlau en Alsace, vers 895, sainte Richarde. Imp&#xE9;ratrice, rejet&#xE9;e par l&#x2019;empereur Charles le Gros, elle entra au monast&#xE8;re qu&#x2019;elle avait fond&#xE9; sur ses terres pour servir Dieu. </para><para id="9">9. &#xC0; Osima dans la Marche d&#x2019;Anc&#xF4;ne, en 1663, saint Joseph de Cupertino, pr&#xEA;tre de l&#x2019;Ordre des Mineurs. Re&#xE7;u chez les conventuels, il se fit remarquer par sa pauvret&#xE9;, son humilit&#xE9; et sa charit&#xE9; envers les pauvres au milieu des circonstances difficiles de sa vie. </para><para id="10">10. &#xC0; Nam Dinh au Tonkin, en 1843, saint Dominique Trach, pr&#xEA;tre de l&#x2019;Ordre des Pr&#xEA;cheurs et martyr. Sous l&#x2019;empereur Minh Mang, il pr&#xE9;f&#xE9;ra la mort plut&#xF4;t que de pi&#xE9;tiner la croix et fut d&#xE9;capit&#xE9;, consommant ainsi son martyre. </para><para id="11">11*. &#xC0; Paimol, pr&#xE8;s de la mission de Kalongi en Ouganda, l&#x2019;an 1918, les bienheureux David Okelo et Gilda Irwa, cat&#xE9;chistes et martyrs. Alors qu&#x2019;ils s&#x2019;employaient &#xE0; enseigner l&#x2019;&#xC9;vangile au peuple, ils furent transperc&#xE9;s de coups de lance par des pa&#xEF;ens du lieu. </para><para id="12">12*. En Espagne, dans la pers&#xE9;cution men&#xE9;e contre les pr&#xEA;tres et les religieux au cours de la guerre civile, en 1936, huit bienheureux martyrs : pr&#xE8;s de Gandie, au pays de Valence, Ferdinand Garcia Sendra et Joseph Garcia Mas, pr&#xEA;tres&#xA0;; &#xE0; Montserrat en Catalogne, cinq membres du Tiers-Ordre de Saint-Fran&#xE7;ois&#xA0;; et &#xE0; Ciudad Real en Nouvelle Castille, Charles Era&#xF1;a Guruceta, religieux de la Soci&#xE9;t&#xE9; de Marie, arr&#xEA;t&#xE9; par des miliciens et fusill&#xE9; sans jugement. </para><para id="13">13*. Au camp de concentration de Dachau en Bavi&#xE8;re, l&#x2019;an 1941, le bienheureux Joseph Kut, pr&#xEA;tre de Poznam et martyr. Arr&#xEA;t&#xE9; par la Gestapo, quand la Pologne fut soumise au r&#xE9;gime nazi, il fut intern&#xE9; et tortur&#xE9; au fort de Poznam, puis d&#xE9;port&#xE9; &#xE0; Dachau, o&#xF9; il mourut de faim. </para></martyrologe><compendium/></calendarium>
